README.md
setup.py
fsleyes_plugin_roitools/__init__.py
fsleyes_plugin_roitools/plugin.py
fsleyes_plugin_roitools.egg-info/PKG-INFO
fsleyes_plugin_roitools.egg-info/SOURCES.txt
fsleyes_plugin_roitools.egg-info/dependency_links.txt
fsleyes_plugin_roitools.egg-info/entry_points.txt
fsleyes_plugin_roitools.egg-info/top_level.txt