Metadata-Version: 2.1
Name: fsleyes-plugin-roitools
Version: 0.0.5
Summary: FSLeyes plugin to work with ROIs
Home-page: https://bitbucket.org/gaunab/fsleyes-plugin-roitool
Author: Paul Kuntke
Author-email: paul.kuntke@tu-dresden.de
License: UNKNOWN
Platform: UNKNOWN
Classifier: Programming Language :: Python :: 3
Classifier: License :: OSI Approved :: MIT License
Classifier: Operating System :: OS Independent
